rul_pm/__init__.py
rul_pm/graphics/__init__.py
rul_pm/graphics/control_charts.py
rul_pm/graphics/duration.py
rul_pm/graphics/embedding.py
rul_pm/graphics/feature_importance.py
rul_pm/graphics/plots.py
rul_pm/graphics/utils/__init__.py
rul_pm/graphics/utils/curly_brace.py
rul_pm/models/DANN.py
rul_pm/models/__init__.py
rul_pm/models/baseline.py
rul_pm/models/fused_lasso.py
rul_pm/models/gradientboosting.py
rul_pm/models/model.py
rul_pm/models/selection.py
rul_pm/models/sklearn.py
rul_pm/models/keras/__init__.py
rul_pm/models/keras/activations.py
rul_pm/models/keras/attention.py
rul_pm/models/keras/callbacks.py
rul_pm/models/keras/extras.py
rul_pm/models/keras/keras.py
rul_pm/models/keras/layers.py
rul_pm/models/keras/losses.py
rul_pm/models/keras/weibull.py
rul_pm/models/keras/models/CNLSTM.py
rul_pm/models/keras/models/ConvEncoderDecoder.py
rul_pm/models/keras/models/InceptionTime.py
rul_pm/models/keras/models/MVCNN.py
rul_pm/models/keras/models/MultiScaleConvolutional.py
rul_pm/models/keras/models/MultiTaskRUL.py
rul_pm/models/keras/models/VisionTransformer.py
rul_pm/models/keras/models/XCM.py
rul_pm/models/keras/models/XiangQiangJianQiao.py
rul_pm/models/keras/models/__init__.py
rul_pm/models/keras/models/simple.py
rul_pm/models/torch/__init__.py
rul_pm/models/torch/dsanet.py
rul_pm/models/torch/model.py
rul_pm/results/__init__.py
rul_pm/results/picewise_regression.py
rul_pm/results/results.py
rul_pm/utils/__init__.py
rul_pm/utils/download.py
rul_pm-0.2.1.dist-info/LICENSE
rul_pm-0.2.1.dist-info/METADATA
rul_pm-0.2.1.dist-info/WHEEL
rul_pm-0.2.1.dist-info/top_level.txt
rul_pm-0.2.1.dist-info/RECORD
